yourag/__init__.py
yourag/ai/base.py
yourag/ai/embeddings.py
yourag/ai/generators.py
yourag/ai/openai_llm.py
yourag/ai/prompts.py
yourag/cli/commands/base.py
yourag/cli/commands/ingest.py
yourag/cli/commands/query.py
yourag/cli/commands/store.py
yourag/cli/main.py
yourag/core/configs/chroma_config.py
yourag/core/configs/yt_config.py
yourag/transcript/base.py
yourag/utils/file_utils.py
yourag/utils/urls.py
yourag/vector_stores/base.py
yourag/vector_stores/chroma_store.py
yourag/youtube/client.py
yourag/youtube/models.py
yourag/youtube/video.py
yourag-0.1.5.dist-info/WHEEL
yourag-0.1.5.dist-info/entry_points.txt
yourag-0.1.5.dist-info/METADATA
yourag-0.1.5.dist-info/RECORD
